pylookup/__init__.py
pylookup/main.py
pylookup/app/__init__.py
pylookup/app/core.py
pylookup/app/gui.py
pylookup/app/parser.py
pylookup/app/servers.py
pylookup/app/utils.py
pylookup_tool-0.1.1.dist-info/LICENSE.md
pylookup_tool-0.1.1.dist-info/METADATA
pylookup_tool-0.1.1.dist-info/WHEEL
pylookup_tool-0.1.1.dist-info/entry_points.txt
pylookup_tool-0.1.1.dist-info/top_level.txt
pylookup_tool-0.1.1.dist-info/RECORD
