Metadata-Version: 2.1
Name: pylookup-tool
Version: 0.1.1
Summary: A CLI tool for WHOIS Lookup Operations
Home-page: https://github.com/h471x/whois_lookup
Author: Hatix Ntsoa
Author-email: hatixntsoa@gmail.com
License: MIT
Classifier: Programming Language :: Python :: 3
Classifier: License :: OSI Approved :: MIT License
Classifier: Operating System :: OS Independent
License-File: LICENSE.md
